README.md
setup.cfg
setup.py
xsera/__init__.py
xsera/avatars.py
xsera/colors.py
xsera/nicknames.py
xsera/proxy_helper.py
xsera.egg-info/PKG-INFO
xsera.egg-info/SOURCES.txt
xsera.egg-info/dependency_links.txt
xsera.egg-info/requires.txt
xsera.egg-info/top_level.txt
xsera/utils/__init__.py
xsera/utils/exceptions.py
xsera/utils/utils.py