Metadata-Version: 2.1
Name: xsera
Version: 1.1.2
Summary: A library to simplify color manipulation, name generation, and more.
Home-page: https://github.com/xXxCLOTIxXx/xsera
Author: Xsarz
Author-email: xsarzy@gmail.com
License: MIT
Download-URL: https://github.com/xXxCLOTIxXx/amino.api/archive/refs/heads/main.zip
Keywords: tools,avatars,nicknames,pymino,colorspython,python3,python3.x,xsarz,official,xsera,xsera.py
Platform: UNKNOWN
